[
  {
    "geo_id": "610345",
    "city": "Campbell",
    "cases": "2094",
    "population": "42470",
    "rate": "4931"
  },
  {
    "geo_id": "617610",
    "city": "Cupertino",
    "cases": "940",
    "population": "60614",
    "rate": "1551"
  },
  {
    "geo_id": "629504",
    "city": "Gilroy",
    "cases": "7582",
    "population": "55525",
    "rate": "13655"
  },
  {
    "geo_id": "643280",
    "city": "Los Altos",
    "cases": "686",
    "population": "30588",
    "rate": "2243"
  },
  {
    "geo_id": "643294",
    "city": "Los Altos Hills",
    "cases": "238",
    "population": "8517",
    "rate": "2794"
  },
  {
    "geo_id": "644112",
    "city": "Los Gatos",
    "cases": "1217",
    "population": "30922",
    "rate": "3936"
  },
  {
    "geo_id": "647766",
    "city": "Milpitas",
    "cases": "3678",
    "population": "77457",
    "rate": "4748"
  },
  {
    "geo_id": "648956",
    "city": "Monte Sereno",
    "cases": "95",
    "population": "3492",
    "rate": "2721"
  },
  {
    "geo_id": "649278",
    "city": "Morgan Hill",
    "cases": "3619",
    "population": "43876",
    "rate": "8248"
  },
  {
    "geo_id": "649670",
    "city": "Mountain View",
    "cases": "3082",
    "population": "80993",
    "rate": "3805"
  },
  {
    "geo_id": "0",
    "city": "Other/Unknown",
    "cases": "4213",
    "population": "0"
  },
  {
    "geo_id": "655282",
    "city": "Palo Alto",
    "cases": "1521",
    "population": "67019",
    "rate": "2270"
  },
  {
    "geo_id": "668000",
    "city": "San Jose",
    "cases": "77949",
    "population": "1026658",
    "rate": "7592"
  },
  {
    "geo_id": "669084",
    "city": "Santa Clara",
    "cases": "5578",
    "population": "126209",
    "rate": "4420"
  },
  {
    "geo_id": "670280",
    "city": "Saratoga",
    "cases": "659",
    "population": "30886",
    "rate": "2134"
  },
  {
    "geo_id": "677000",
    "city": "Sunnyvale",
    "cases": "5645",
    "population": "152323",
    "rate": "3706"
  }
]
